[
  {
    "alarmID": 1,
    "userID": 1,
    "workplaceID": 1,
    "status": true,
    "adjustDate": "2023-12-18",
    "person": "김희환",
    "startTime": "10:00",
    "content": "근무자를 배정할 지 확인해주세요."
  },
  {
    "alarmID": 2,
    "userID": 1,
    "workplaceID": 2,
    "status": true,
    "adjustDate": "2023-12-18",
    "person": "김태현",
    "startTime": "10:00",
    "content": "근무자를 배정할 지 확인해주세요."
  },
  {
    "alarmID": 3,
    "userID": 1,
    "workplaceID": 1,
    "status": true,
    "adjustDate": "2023-11-30",
    "person": "송승우",
    "startTime": "9:00",
    "content": "근무자를 배정할 지 확인해주세요."
  },
  {
    "alarmID": 4,
    "userID": 1,
    "workplaceID": 1,
    "status": true,
    "adjustDate": "2023-11-18",
    "person": "구교민",
    "startTime": "13:00",
    "content": "근무자를 배정할 지 확인해주세요."
  }
]